wtd/__init__.py
wtd/__version__.py
wtd-0.0.1.dev1.dist-info/METADATA
wtd-0.0.1.dev1.dist-info/WHEEL
wtd-0.0.1.dev1.dist-info/top_level.txt
wtd-0.0.1.dev1.dist-info/RECORD
