Metadata-Version: 2.1
Name: wtd
Version: 0.0.1.dev1
Summary: UNKNOWN
Home-page: https://github.com/ddnomad/wtd
Author: ddnomad
Author-email: self@ddnomad.io
License: UNKNOWN
Project-URL: Documentation, https://github.com/ddnomad/wtd
Project-URL: Source, https://github.com/ddnomad/wtd
Platform: UNKNOWN
Classifier: Development Status :: 1 - Planning
Classifier: Environment :: Console
Classifier: Intended Audience :: Developers
Classifier: Natural Language :: English
Classifier: Operating System :: POSIX
Classifier: Programming Language :: Python :: 3.7
Classifier: Programming Language :: Python :: 3.8
Classifier: Programming Language :: Python :: 3.9
Classifier: Programming Language :: Python :: 3.10
Classifier: Topic :: Utilities
Requires-Python: >=3.7
Requires-Dist: beartype (==0.10.4)
Requires-Dist: coloredlogs (==15.0.1)
Requires-Dist: commonmark (==0.9.1)
Requires-Dist: humanfriendly (==10.0)
Requires-Dist: pygments (==2.11.2)
Requires-Dist: rich (==12.0.1)
Requires-Dist: semantic-version (==2.9.0)
